{
    "users": {
        "Akashi_12": {
            "offers": {
                "8797311": [
                    "8758937",
                    "8763937",
                    "8763945",
                    "8769894"
                ],
                "8797321": [
                    "8758937",
                    "8763937",
                    "8763945",
                    "8769894"
                ],
                "8797327": [],
                "8797339": [
                    "8758937",
                    "8763937",
                    "8763945",
                    "8769894"
                ],
                "8797344": [
                    "8758937",
                    "8763937",
                    "8763945",
                    "8769894"
                ]
            }
        },
        "aslaksen": {
            "offers": {
                "8795390": [],
                "8795394": [],
                "8795439": [],
                "8795443": [
                    "8794508",
                    "8801658"
                ],
                "8795445": [
                    "8794508",
                    "8801658",
                    "8794498",
                    "8794495",
                    "8794502",
                    "8769872"
                ],
                "8795446": [
                    "8794508",
                    "8801658",
                    "8794498",
                    "8794495",
                    "8794502",
                    "8769872"
                ],
                "8795462": [
                    "8794508",
                    "8801658",
                    "8794498",
                    "8794495",
                    "8794502",
                    "8769872"
                ],
                "8795464": [
                    "8794508",
                    "8801658",
                    "8794498",
                    "8794495",
                    "8794502",
                    "8769872"
                ],
                "8795466": [
                    "8794508",
                    "8801658",
                    "8794498",
                    "8794495",
                    "8794502",
                    "8769872"
                ],
                "8795469": [
                    "8794508",
                    "8801658",
                    "8794498",
                    "8794495",
                    "8794502",
                    "8769872"
                ],
                "8795470": [
                    "8794508",
                    "8801658",
                    "8794498",
                    "8794495",
                    "8794502",
                    "8769872"
                ],
                "8795471": [
                    "8794508",
                    "8801658",
                    "8794498",
                    "8794495",
                    "8794502",
                    "8769872"
                ],
                "8798163": [],
                "8798164": []
            }
        },
        "catzy": {
            "offers": {
                "8764245": [
                    "8795394",
                    "8794509",
                    "8795390",
                    "8794503",
                    "8794516",
                    "8777573",
                    "8794499",
                    "8793712"
                ],
                "8764280": [
                    "8795394",
                    "8794509",
                    "8795390",
                    "8794503",
                    "8794516",
                    "8777573",
                    "8794499",
                    "8793712"
                ]
            }
        },
        "Gawain": {
            "offers": {
                "8801636": [
                    "8795390"
                ],
                "8801639": [
                    "8795390"
                ],
                "8801642": [
                    "8795390",
                    "8758940"
                ],
                "8801644": [
                    "8795390",
                    "8758940",
                    "8794509",
                    "8758937",
                    "8763937"
                ],
                "8801645": [
                    "8795390",
                    "8758940",
                    "8794509",
                    "8758937",
                    "8763937",
                    "8798164"
                ],
                "8801647": [
                    "8795390",
                    "8758940",
                    "8794509",
                    "8758937",
                    "8763937",
                    "8798164"
                ],
                "8801648": [
                    "8795390"
                ],
                "8801649": [],
                "8801651": [
                    "8795390",
                    "8758940",
                    "8794509",
                    "8758937",
                    "8763937",
                    "8798164"
                ],
                "8801653": [
                    "8795390"
                ],
                "8801655": [
                    "8795390",
                    "8758940",
                    "8794509",
                    "8758937",
                    "8763937",
                    "8798164"
                ],
                "8801656": [
                    "8795390",
                    "8758940",
                    "8794509",
                    "8758937",
                    "8763937",
                    "8798164"
                ],
                "8801657": [
                    "8795390",
                    "8758940",
                    "8794509",
                    "8758937",
                    "8763937",
                    "8798164"
                ],
                "8801658": [
                    "8795390",
                    "8758940"
                ]
            }
        },
        "Kvamzi": {
            "offers": {
                "8758926": [
                    "8777492",
                    "8777548"
                ],
                "8758927": [
                    "8777492",
                    "8777548",
                    "8777552",
                    "8794509"
                ],
                "8758928": [
                    "8777492",
                    "8777548",
                    "8777552",
                    "8794509",
                    "8795439"
                ],
                "8758930": [
                    "8777492",
                    "8777548",
                    "8777552",
                    "8794509",
                    "8795439",
                    "8801658"
                ],
                "8758931": [
                    "8777492",
                    "8777548",
                    "8777552",
                    "8794509",
                    "8795439",
                    "8801658"
                ],
                "8758932": [
                    "8777492",
                    "8777548",
                    "8777552",
                    "8794509",
                    "8795439"
                ],
                "8758933": [
                    "8777492",
                    "8777548",
                    "8777552",
                    "8794509",
                    "8795439"
                ],
                "8758934": [
                    "8777492",
                    "8777548",
                    "8777552",
                    "8794509",
                    "8795439"
                ],
                "8758936": [
                    "8777492",
                    "8777548",
                    "8777552",
                    "8794509"
                ],
                "8758937": [],
                "8758938": [
                    "8777492",
                    "8777548",
                    "8777552"
                ],
                "8758939": [
                    "8777492",
                    "8777548"
                ],
                "8758940": []
            }
        },
        "nils777": {
            "offers": {
                "8793683": [
                    "8795394",
                    "8779179",
                    "8779159",
                    "8781912",
                    "8771609",
                    "8777548"
                ],
                "8793686": [
                    "8795394",
                    "8779179",
                    "8779159",
                    "8781912",
                    "8771609",
                    "8777548"
                ],
                "8793689": [
                    "8795394",
                    "8779179",
                    "8779159",
                    "8781912",
                    "8771609",
                    "8777548",
                    "8777582",
                    "8794508",
                    "8781909",
                    "8771680"
                ],
                "8793692": [
                    "8795394",
                    "8779179",
                    "8779159",
                    "8781912",
                    "8771609",
                    "8777548",
                    "8777582",
                    "8794508",
                    "8781909",
                    "8771680",
                    "8781904",
                    "8771603",
                    "8771597",
                    "8794509",
                    "8794516",
                    "8794499",
                    "8794498"
                ],
                "8793693": [
                    "8795394",
                    "8779179",
                    "8779159",
                    "8781912",
                    "8771609",
                    "8777548",
                    "8777582",
                    "8794508",
                    "8781909",
                    "8771680",
                    "8781904",
                    "8771603",
                    "8771597"
                ],
                "8793698": [
                    "8795394",
                    "8779179",
                    "8779159",
                    "8781912",
                    "8771609",
                    "8777548",
                    "8777582",
                    "8794508",
                    "8781909",
                    "8771680",
                    "8781904",
                    "8771603",
                    "8771597",
                    "8794509",
                    "8794516",
                    "8794499"
                ],
                "8793702": [],
                "8793706": [
                    "8795394",
                    "8779179",
                    "8779159",
                    "8781912",
                    "8771609",
                    "8777548",
                    "8777582",
                    "8794508",
                    "8781909",
                    "8771680",
                    "8781904",
                    "8771603",
                    "8771597",
                    "8794509",
                    "8794516",
                    "8794499",
                    "8794498"
                ],
                "8793711": [
                    "8795394",
                    "8779179",
                    "8779159",
                    "8781912",
                    "8771609",
                    "8777548",
                    "8777582",
                    "8794508",
                    "8781909",
                    "8771680",
                    "8781904",
                    "8771603",
                    "8771597",
                    "8794509",
                    "8794516",
                    "8794499",
                    "8794498"
                ],
                "8793712": [
                    "8795394",
                    "8779179",
                    "8779159",
                    "8781912",
                    "8771609",
                    "8777548",
                    "8777582",
                    "8794508",
                    "8781909",
                    "8771680",
                    "8781904",
                    "8771603",
                    "8771597",
                    "8794509",
                    "8794516",
                    "8794499",
                    "8794498"
                ],
                "8793714": [
                    "8795394",
                    "8779179",
                    "8779159",
                    "8781912",
                    "8771609",
                    "8777548",
                    "8777582",
                    "8794508",
                    "8781909",
                    "8771680",
                    "8781904",
                    "8771603",
                    "8771597",
                    "8794509",
                    "8794516",
                    "8794499",
                    "8794498"
                ],
                "8793715": [
                    "8795394",
                    "8779179",
                    "8779159",
                    "8781912",
                    "8771609",
                    "8777548",
                    "8777582",
                    "8794508",
                    "8781909",
                    "8771680",
                    "8781904",
                    "8771603",
                    "8771597",
                    "8794509",
                    "8794516",
                    "8794499",
                    "8794498"
                ]
            }
        },
        "Postbb": {
            "offers": {
                "8771597": [
                    "8777548",
                    "8763931",
                    "8777492",
                    "8800395",
                    "8758940",
                    "8794510",
                    "8797327",
                    "8795390",
                    "8801658"
                ],
                "8771603": [
                    "8777548",
                    "8763931",
                    "8777492",
                    "8800395",
                    "8758940",
                    "8794510",
                    "8797327",
                    "8795390",
                    "8801658",
                    "8793689",
                    "8795394",
                    "8779175",
                    "8763860",
                    "8794516",
                    "8758926",
                    "8794499",
                    "8794513",
                    "8793714"
                ],
                "8771609": [
                    "8777548",
                    "8763931"
                ],
                "8771659": [
                    "8777548",
                    "8763931",
                    "8777492",
                    "8800395",
                    "8758940",
                    "8794510",
                    "8797327",
                    "8795390",
                    "8801658",
                    "8793689",
                    "8795394",
                    "8779175",
                    "8763860",
                    "8794516",
                    "8758926",
                    "8794499",
                    "8794513",
                    "8793714"
                ],
                "8771663": [
                    "8777548",
                    "8763931",
                    "8777492",
                    "8800395",
                    "8758940",
                    "8794510",
                    "8797327",
                    "8795390",
                    "8801658",
                    "8793689",
                    "8795394",
                    "8779175",
                    "8763860",
                    "8794516",
                    "8758926",
                    "8794499",
                    "8794513",
                    "8793714"
                ],
                "8771665": [
                    "8777548",
                    "8763931",
                    "8777492",
                    "8800395",
                    "8758940",
                    "8794510",
                    "8797327",
                    "8795390",
                    "8801658",
                    "8793689",
                    "8795394",
                    "8779175",
                    "8763860",
                    "8794516",
                    "8758926",
                    "8794499",
                    "8794513",
                    "8793714"
                ],
                "8771680": [
                    "8777548",
                    "8763931",
                    "8777492",
                    "8800395",
                    "8758940",
                    "8794510",
                    "8797327",
                    "8795390",
                    "8801658",
                    "8793689"
                ]
            }
        },
        "Rune": {
            "offers": {
                "8777573": [
                    "8763945",
                    "8798163"
                ],
                "8777574": [
                    "8763945"
                ],
                "8777576": [
                    "8763945"
                ],
                "8777578": [
                    "8763945",
                    "8798163",
                    "8801658",
                    "8769900"
                ],
                "8777582": [
                    "8763945"
                ]
            }
        },
        "Spilljeger": {
            "offers": {
                "8794478": [
                    "8763945",
                    "8758939"
                ],
                "8794484": [
                    "8763945",
                    "8777578",
                    "8793698",
                    "8758939"
                ],
                "8794489": [
                    "8763945",
                    "8777578",
                    "8793698",
                    "8797321"
                ],
                "8794495": [
                    "8763945",
                    "8777578",
                    "8758939"
                ],
                "8794498": [
                    "8758939"
                ],
                "8794499": [
                    "8793698",
                    "8797321"
                ],
                "8794500": [
                    "8797321"
                ],
                "8794502": [
                    "8763945",
                    "8758939"
                ],
                "8794503": [
                    "8793698",
                    "8797321"
                ],
                "8794508": [
                    "8777578",
                    "8793698",
                    "8797321"
                ],
                "8794509": [
                    "8763945",
                    "8777578",
                    "8793698",
                    "8797321"
                ],
                "8794510": [
                    "8763945",
                    "8777578",
                    "8758939"
                ],
                "8794513": [
                    "8763945",
                    "8777578",
                    "8793698",
                    "8758939"
                ],
                "8794514": [
                    "8777578",
                    "8793698",
                    "8797321"
                ],
                "8794515": [
                    "8763945",
                    "8777578",
                    "8793698",
                    "8797321"
                ],
                "8794516": [
                    "8758939"
                ],
                "8794517": [
                    "8797321"
                ],
                "8794518": [
                    "8763945",
                    "8777578",
                    "8793698",
                    "8797321"
                ]
            }
        },
        "StoneHead": {
            "offers": {
                "8779159": [
                    "8758939",
                    "8795394",
                    "8763945",
                    "8777492",
                    "8777582",
                    "8794508",
                    "8763931",
                    "8763860",
                    "8794516",
                    "8801636",
                    "8801658"
                ],
                "8779164": [
                    "8758939",
                    "8795394",
                    "8763945",
                    "8777492",
                    "8777582",
                    "8794508",
                    "8763931",
                    "8763860",
                    "8794516",
                    "8801636"
                ],
                "8779166": [
                    "8758939",
                    "8795394",
                    "8763945",
                    "8777492",
                    "8777582",
                    "8794508",
                    "8763931",
                    "8763860",
                    "8794516",
                    "8801636",
                    "8801658"
                ],
                "8779169": [
                    "8758939",
                    "8795394",
                    "8763945",
                    "8777492",
                    "8777582",
                    "8794508",
                    "8763931",
                    "8763860",
                    "8794516",
                    "8801636",
                    "8801658"
                ],
                "8779175": [
                    "8758939",
                    "8795394",
                    "8763945",
                    "8777492",
                    "8777582",
                    "8794508",
                    "8763931",
                    "8763860",
                    "8794516",
                    "8801636",
                    "8801658"
                ],
                "8779179": [
                    "8758939",
                    "8795394",
                    "8763945"
                ]
            }
        },
        "terningkast7": {
            "offers": {
                "8781898": [
                    "8758939",
                    "8795394",
                    "8771609",
                    "8795390",
                    "8763931",
                    "8771597",
                    "8777492",
                    "8777582",
                    "8763860",
                    "8793686",
                    "8794516",
                    "8794499",
                    "8769872",
                    "8758930"
                ],
                "8781899": [
                    "8758939",
                    "8795394",
                    "8771609",
                    "8795390",
                    "8763931",
                    "8771597",
                    "8777492",
                    "8777582",
                    "8763860",
                    "8793686",
                    "8794516",
                    "8794499",
                    "8769872",
                    "8758930"
                ],
                "8781904": [
                    "8758939",
                    "8795394",
                    "8771609",
                    "8795390",
                    "8763931",
                    "8771597",
                    "8777492",
                    "8777582",
                    "8763860",
                    "8793686",
                    "8794516",
                    "8794499",
                    "8769872",
                    "8758930"
                ],
                "8781908": [
                    "8758939",
                    "8795394",
                    "8771609",
                    "8795390",
                    "8763931",
                    "8771597",
                    "8777492",
                    "8777582",
                    "8763860",
                    "8793686",
                    "8794516",
                    "8794499",
                    "8769872",
                    "8758930"
                ],
                "8781909": [
                    "8758939",
                    "8795394",
                    "8771609",
                    "8795390",
                    "8763931",
                    "8771597",
                    "8777492",
                    "8777582",
                    "8763860",
                    "8793686",
                    "8794516",
                    "8794499",
                    "8769872",
                    "8758930"
                ],
                "8781912": [
                    "8758939",
                    "8795394",
                    "8771609",
                    "8795390",
                    "8763931",
                    "8771597",
                    "8777492",
                    "8777582",
                    "8763860",
                    "8793686",
                    "8794516",
                    "8794499",
                    "8769872",
                    "8758930"
                ],
                "8781919": [
                    "8758939",
                    "8795394",
                    "8771609",
                    "8795390",
                    "8763931",
                    "8771597",
                    "8777492",
                    "8777582",
                    "8763860",
                    "8793686",
                    "8794516",
                    "8794499",
                    "8769872",
                    "8758930"
                ]
            }
        },
        "trilb": {
            "offers": {
                "8800395": [
                    "8777492"
                ]
            }
        }
    },
    "items": {
        "8758926": {
            "name": "KeyForge: Call of the Archons",
            "owner": "Kvamzi"
        },
        "8758927": {
            "name": "Battleground: Crossbows & Catapults",
            "owner": "Kvamzi"
        },
        "8758928": {
            "name": "Risk",
            "owner": "Kvamzi"
        },
        "8758930": {
            "name": "Small World: Tales and Legends",
            "owner": "Kvamzi"
        },
        "8758931": {
            "name": "Tichu",
            "owner": "Kvamzi"
        },
        "8758932": {
            "name": "Sorry! Sliders",
            "owner": "Kvamzi"
        },
        "8758933": {
            "name": "Wanna Bet?",
            "owner": "Kvamzi"
        },
        "8758934": {
            "name": "Niagara",
            "owner": "Kvamzi"
        },
        "8758936": {
            "name": "Elfenland",
            "owner": "Kvamzi"
        },
        "8758937": {
            "name": "Formula D",
            "owner": "Kvamzi"
        },
        "8758938": {
            "name": "Mr. Jack",
            "owner": "Kvamzi"
        },
        "8758939": {
            "name": "PitchCar",
            "owner": "Kvamzi"
        },
        "8758940": {
            "name": "Space Alert",
            "owner": "Kvamzi"
        },
        "8762739": {
            "name": "Age of Thieves",
            "owner": "takras"
        },
        "8763860": {
            "name": "Petrichor",
            "owner": "bdeink"
        },
        "8763921": {
            "name": "Risk: Transformers – Cybertron Battle Edition",
            "owner": "bdeink"
        },
        "8763931": {
            "name": "Burgle Bros 2: The Casino Capers",
            "owner": "bdeink"
        },
        "8763937": {
            "name": "Myrmes",
            "owner": "bdeink"
        },
        "8763943": {
            "name": "Caverna: The Forgotten Folk",
            "owner": "bdeink"
        },
        "8763945": {
            "name": "Virgin Queen",
            "owner": "bdeink"
        },
        "8763953": {
            "name": "Torres",
            "owner": "bdeink"
        },
        "8764245": {
            "name": "Fabled Fruit",
            "owner": "Catzy"
        },
        "8764280": {
            "name": "Green Box of Games",
            "owner": "Catzy"
        },
        "8769861": {
            "name": "Mascarade",
            "owner": "bdeink"
        },
        "8769864": {
            "name": "Al Cabohne",
            "owner": "bdeink"
        },
        "8769871": {
            "name": "Cosmocracy",
            "owner": "bdeink"
        },
        "8769872": {
            "name": "Rebel Nox",
            "owner": "bdeink"
        },
        "8769879": {
            "name": "Risk: The Lord of the Rings",
            "owner": "bdeink"
        },
        "8769890": {
            "name": "Tikal",
            "owner": "bdeink"
        },
        "8769894": {
            "name": "For the People",
            "owner": "bdeink"
        },
        "8769898": {
            "name": "Diplomacy",
            "owner": "bdeink"
        },
        "8769900": {
            "name": "13 Minutes: The Cuban Missile Crisis, 1962",
            "owner": "bdeink"
        },
        "8771597": {
            "name": "Detective: A Modern Crime Board Game – Season One",
            "owner": "postbb"
        },
        "8771603": {
            "name": "Hera and Zeus",
            "owner": "postbb"
        },
        "8771609": {
            "name": "Detective: A Modern Crime Board Game",
            "owner": "postbb"
        },
        "8771659": {
            "name": "Choose Your Own Adventure: House of Danger",
            "owner": "postbb"
        },
        "8771663": {
            "name": "Player's Handbook (D&D 3e)",
            "owner": "postbb"
        },
        "8771665": {
            "name": "Chez Geek",
            "owner": "postbb"
        },
        "8771680": {
            "name": "Unlock!: Escape Adventures",
            "owner": "postbb"
        },
        "8777492": {
            "name": "Inis",
            "owner": "Chillstad"
        },
        "8777548": {
            "name": "Dead of Winter: The Long Night",
            "owner": "Chillstad"
        },
        "8777552": {
            "name": "Cosmic Encounter",
            "owner": "Chillstad"
        },
        "8777573": {
            "name": "The Ark of the Covenant",
            "owner": "Rune"
        },
        "8777574": {
            "name": "Wallenstein",
            "owner": "Rune"
        },
        "8777576": {
            "name": "Quartermaster General",
            "owner": "Rune"
        },
        "8777578": {
            "name": "W1815",
            "owner": "Rune"
        },
        "8777582": {
            "name": "Thurn and Taxis",
            "owner": "Rune"
        },
        "8779159": {
            "name": "Through the Ages: A Story of Civilization",
            "owner": "StoneHead"
        },
        "8779164": {
            "name": "Super Cluedo Challenge",
            "owner": "StoneHead"
        },
        "8779166": {
            "name": "Age of Towers",
            "owner": "StoneHead"
        },
        "8779169": {
            "name": "Ave Roma",
            "owner": "StoneHead"
        },
        "8779175": {
            "name": "Eminent Domain",
            "owner": "StoneHead"
        },
        "8779179": {
            "name": "Railways of the World",
            "owner": "StoneHead"
        },
        "8781898": {
            "name": "Metropoli",
            "owner": "Terningkast7"
        },
        "8781899": {
            "name": "Dominion: Cornucopia",
            "owner": "Terningkast7"
        },
        "8781904": {
            "name": "Ca$h 'n Gun$",
            "owner": "Terningkast7"
        },
        "8781908": {
            "name": "Guards! Guards! A Discworld Boardgame",
            "owner": "Terningkast7"
        },
        "8781909": {
            "name": "The Lord of the Rings",
            "owner": "Terningkast7"
        },
        "8781912": {
            "name": "Steam",
            "owner": "Terningkast7"
        },
        "8781919": {
            "name": "Rolling Freight",
            "owner": "Terningkast7"
        },
        "8793683": {
            "name": "La Città",
            "owner": "nils777"
        },
        "8793686": {
            "name": "Giants",
            "owner": "nils777"
        },
        "8793689": {
            "name": "Power Grid",
            "owner": "nils777"
        },
        "8793692": {
            "name": "A Game of Thrones: The Card Game",
            "owner": "nils777"
        },
        "8793693": {
            "name": "Sultaniya",
            "owner": "nils777"
        },
        "8793698": {
            "name": "Ticket to Ride: The Card Game",
            "owner": "nils777"
        },
        "8793702": {
            "name": "Sultaniya",
            "owner": "nils777"
        },
        "8793706": {
            "name": "Batavia",
            "owner": "nils777"
        },
        "8793711": {
            "name": "Arkham Ritual",
            "owner": "nils777"
        },
        "8793712": {
            "name": "Catan: Traders & Barbarians – 5-6 Player Extension",
            "owner": "nils777"
        },
        "8793714": {
            "name": "Onward to Venus",
            "owner": "nils777"
        },
        "8793715": {
            "name": "Eight-Minute Empire",
            "owner": "nils777"
        },
        "8794478": {
            "name": "Spooky Stairs",
            "owner": "Spilljeger"
        },
        "8794484": {
            "name": "The Siege of Jerusalem (Third Edition)",
            "owner": "Spilljeger"
        },
        "8794489": {
            "name": "Firepower",
            "owner": "Spilljeger"
        },
        "8794495": {
            "name": "Diamonds: Second Edition",
            "owner": "Spilljeger"
        },
        "8794498": {
            "name": "BANG! The Dice Game",
            "owner": "Spilljeger"
        },
        "8794499": {
            "name": "Villages of Valeria",
            "owner": "Spilljeger"
        },
        "8794500": {
            "name": "VivaJava: The Coffee Game: The Dice Game",
            "owner": "Spilljeger"
        },
        "8794502": {
            "name": "Dead Man's Draw",
            "owner": "Spilljeger"
        },
        "8794503": {
            "name": "My First Stone Age",
            "owner": "Spilljeger"
        },
        "8794508": {
            "name": "Trains",
            "owner": "Spilljeger"
        },
        "8794509": {
            "name": "Tokaido",
            "owner": "Spilljeger"
        },
        "8794510": {
            "name": "Star Wars: X-Wing Miniatures Game",
            "owner": "Spilljeger"
        },
        "8794513": {
            "name": "Enchanters",
            "owner": "Spilljeger"
        },
        "8794514": {
            "name": "Hey, That's My Fish!",
            "owner": "Spilljeger"
        },
        "8794515": {
            "name": "Fast Forward: FEAR",
            "owner": "Spilljeger"
        },
        "8794516": {
            "name": "New Bedford",
            "owner": "Spilljeger"
        },
        "8794517": {
            "name": "My Happy Farm",
            "owner": "Spilljeger"
        },
        "8794518": {
            "name": "Tiki Topple",
            "owner": "Spilljeger"
        },
        "8795390": {
            "name": "Alhambra: Big Box",
            "owner": "aslaksen"
        },
        "8795394": {
            "name": "Isle of Skye: From Chieftain to King",
            "owner": "aslaksen"
        },
        "8795439": {
            "name": "Samurai Spirit",
            "owner": "aslaksen"
        },
        "8795443": {
            "name": "Twixt",
            "owner": "aslaksen"
        },
        "8795445": {
            "name": "Ca$h 'n Gun$",
            "owner": "aslaksen"
        },
        "8795446": {
            "name": "Herbalism",
            "owner": "aslaksen"
        },
        "8795462": {
            "name": "Kokoro: Avenue of the Kodama",
            "owner": "aslaksen"
        },
        "8795464": {
            "name": "Bukiet",
            "owner": "aslaksen"
        },
        "8795466": {
            "name": "GPS",
            "owner": "aslaksen"
        },
        "8795469": {
            "name": "Pizza Theory",
            "owner": "aslaksen"
        },
        "8795470": {
            "name": "Shadow Master",
            "owner": "aslaksen"
        },
        "8795471": {
            "name": "Hanamikoji: Deep Water Games Promo",
            "owner": "aslaksen"
        },
        "8797311": {
            "name": "Cadwallon: City of Thieves",
            "owner": "Akashi_12"
        },
        "8797321": {
            "name": "Thud & Blunder: Fantasy Skirmish Wargaming Rules",
            "owner": "Akashi_12"
        },
        "8797327": {
            "name": "Combat Commander: Pacific",
            "owner": "Akashi_12"
        },
        "8797339": {
            "name": "Outside the Scope of BGG",
            "owner": "Akashi_12"
        },
        "8797344": {
            "name": "Retro: Tactical WWII Wargame Variant Rules",
            "owner": "Akashi_12"
        },
        "8798163": {
            "name": "Kingdom Builder",
            "owner": "aslaksen"
        },
        "8798164": {
            "name": "Outside the Scope of BGG",
            "owner": "aslaksen"
        },
        "8800395": {
            "name": "Dungeon Petz",
            "owner": "trilb"
        },
        "8801636": {
            "name": "Bastion",
            "owner": "Gawain"
        },
        "8801639": {
            "name": "Beowulf: The Legend",
            "owner": "Gawain"
        },
        "8801642": {
            "name": "Hanabi",
            "owner": "Gawain"
        },
        "8801644": {
            "name": "HeroClix",
            "owner": "Gawain"
        },
        "8801645": {
            "name": "Jeg har aldri",
            "owner": "Gawain"
        },
        "8801647": {
            "name": "Mamma Mia!",
            "owner": "Gawain"
        },
        "8801648": {
            "name": "Race Through Space",
            "owner": "Gawain"
        },
        "8801649": {
            "name": "Rush n' Crush",
            "owner": "Gawain"
        },
        "8801651": {
            "name": "Space Beans",
            "owner": "Gawain"
        },
        "8801653": {
            "name": "WWE Superstar Showdown",
            "owner": "Gawain"
        },
        "8801655": {
            "name": "Nightfall: Zombie Horde Promo",
            "owner": "Gawain"
        },
        "8801656": {
            "name": "Pathfinder Adventure Card Game: Wrath of the Righteous Adventure Deck 3 – Demon's Heresy",
            "owner": "Gawain"
        },
        "8801657": {
            "name": "Pathfinder Adventure Card Game: Wrath of the Righteous – Character Add-On Deck",
            "owner": "Gawain"
        },
        "8801658": {
            "name": "Alt Name: 200 kroner",
            "owner": "Gawain"
        }
    }
}